macsyfinder/__init__.py
macsyfinder/io.py
macsyfinder/scripts/__init__.py
macsyfinder/scripts/macsy_gembase_split.py
macsyfinder/scripts/macsy_merge_results.py
macsyfinder/scripts/macsyconfig.py
macsyfinder/scripts/macsydata.py
macsyfinder/scripts/macsyprofile.py
macsyfinder/scripts/msf.py
macsyfinder-2.1.6.data/data/share/macsyfinder/doc/html/.buildinfo
macsyfinder-2.1.6.data/data/share/macsyfinder/doc/html/genindex.html
macsyfinder-2.1.6.data/data/share/macsyfinder/doc/html/index.html
macsyfinder-2.1.6.data/data/share/macsyfinder/doc/html/objects.inv
macsyfinder-2.1.6.data/data/share/macsyfinder/doc/html/py-modindex.html
macsyfinder-2.1.6.data/data/share/macsyfinder/doc/html/search.html
macsyfinder-2.1.6.data/data/share/macsyfinder/doc/html/searchindex.js
macsyfinder-2.1.6.data/data/share/macsyfinder/doc/html/_downloads/12424bc65a997e828f664efef9d02f59/pre-push
macsyfinder-2.1.6.data/data/share/macsyfinder/doc/html/_downloads/22d0e9e5cd8bcd00d04c2f13cbab13fa/msf_summary.py
macsyfinder-2.1.6.data/data/share/macsyfinder/doc/html/_images/MSF_modelling.svg
macsyfinder-2.1.6.data/data/share/macsyfinder/doc/html/_images/T1SS_example.svg
macsyfinder-2.1.6.data/data/share/macsyfinder/doc/html/_images/T3SS_example.svg
macsyfinder-2.1.6.data/data/share/macsyfinder/doc/html/_images/figure_main-2.svg
macsyfinder-2.1.6.data/data/share/macsyfinder/doc/html/_images/graphviz-d343e674fd159053aa383b9bbc9e061038f4e4ad.png
macsyfinder-2.1.6.data/data/share/macsyfinder/doc/html/_images/graphviz-d343e674fd159053aa383b9bbc9e061038f4e4ad.png.map
macsyfinder-2.1.6.data/data/share/macsyfinder/doc/html/_images/graphviz-e048f6355ae896b33fbcab05b1235620a715564a.png
macsyfinder-2.1.6.data/data/share/macsyfinder/doc/html/_images/graphviz-e048f6355ae896b33fbcab05b1235620a715564a.png.map
macsyfinder-2.1.6.data/data/share/macsyfinder/doc/html/_images/logo_macsyfinder.png
macsyfinder-2.1.6.data/data/share/macsyfinder/doc/html/_images/logo_macsymodels.png
macsyfinder-2.1.6.dist-info/licenses/COPYING
macsyfinder-2.1.6.dist-info/METADATA
macsyfinder-2.1.6.dist-info/WHEEL
macsyfinder-2.1.6.dist-info/entry_points.txt
macsyfinder-2.1.6.dist-info/top_level.txt
macsyfinder-2.1.6.dist-info/RECORD
