Metadata-Version: 2.4
Name: MacSyFinder
Version: 2.1.6
Summary: MacSyFinder: Detection of macromolecular systems in protein datasets using systems modelling and similarity search
Author-email: Sophie Abby <sophie.abby@univ-grenoble-alpes.fr>, Bertrand Neron <bneron@pasteur.fr>
Maintainer-email: Bertrand Neron <bneron@pasteur.fr>
License-Expression: GPL-3.0-or-later
Project-URL: Homepage, https://github.com/gem-pasteur/macsyfinder/
Project-URL: Documentation, https://macsyfinder.readthedocs.io/en/latest/
Project-URL: Repository, https://github.com/gem-pasteur/macsyfinder/
Project-URL: Issues, https://github.com/gem-pasteur/macsyfinder/issues
Project-URL: Changelog, https://macsyfinder.readthedocs.io/en/latest/user_guide/new_v2.html#what-s-new-in-macsyfinder-v2
Keywords: science,research,bioinformatic,microbiology,genomic,prokaryote,functional gene annotation
Classifier: Programming Language :: Python :: 3
Classifier: Programming Language :: Python :: 3.10
Classifier: Programming Language :: Python :: 3.11
Classifier: Programming Language :: Python :: 3.12
Classifier: Programming Language :: Python :: 3.13
Classifier: Programming Language :: Python :: 3.14
Classifier: Operating System :: POSIX
Classifier: Environment :: Console
Classifier: Development Status :: 5 - Production/Stable
Classifier: Intended Audience :: Science/Research
Classifier: Topic :: Scientific/Engineering :: Bio-Informatics
Requires-Python: >=3.10
License-File: COPYING
Requires-Dist: macsylib<3,>=1.0.4
Provides-Extra: dev
Requires-Dist: macsylib[dev]<3,>=1.0.4; extra == "dev"
Requires-Dist: sphinx; extra == "dev"
Requires-Dist: sphinx_rtd_theme; extra == "dev"
Requires-Dist: sphinx-autodoc-typehints; extra == "dev"
Requires-Dist: sphinxcontrib-svg2pdfconverter; extra == "dev"
Requires-Dist: coverage[toml]; extra == "dev"
Requires-Dist: build; extra == "dev"
Requires-Dist: ruff; extra == "dev"
Requires-Dist: pre-commit; extra == "dev"
Provides-Extra: model
Requires-Dist: macsylib[model]<3,>=1.0.4; extra == "model"
Dynamic: license-file
